cliriculum/__init__.py
cliriculum/deserializers.py
cliriculum/loaders.py
cliriculum/main.py
cliriculum/markdown.py
cliriculum/parsers.py
cliriculum/pdf.py
cliriculum/renderers.py
cliriculum/resume.py
cliriculum/utils.py
cliriculum/data/__init__.py
cliriculum/data/paged.polyfill.js
cliriculum/data/style.css
cliriculum/data/style.js
cliriculum/data/fontawesome/LICENSE.txt
cliriculum/data/fontawesome/__init__.py
cliriculum/data/fontawesome/css/__init__.py
cliriculum/data/fontawesome/css/all.css
cliriculum/data/fontawesome/css/all.min.css
cliriculum/data/fontawesome/css/v4-shims.css
cliriculum/data/fontawesome/css/v4-shims.min.css
cliriculum/data/fontawesome/webfonts/__init__.py
cliriculum/data/fontawesome/webfonts/fa-brands-400.ttf
cliriculum/data/fontawesome/webfonts/fa-brands-400.woff2
cliriculum/data/fontawesome/webfonts/fa-regular-400.ttf
cliriculum/data/fontawesome/webfonts/fa-regular-400.woff2
cliriculum/data/fontawesome/webfonts/fa-solid-900.ttf
cliriculum/data/fontawesome/webfonts/fa-solid-900.woff2
cliriculum/data/fontawesome/webfonts/fa-v4compatibility.ttf
cliriculum/data/fontawesome/webfonts/fa-v4compatibility.woff2
cliriculum-0.2.2.dist-info/LICENSE.md
cliriculum-0.2.2.dist-info/METADATA
cliriculum-0.2.2.dist-info/WHEEL
cliriculum-0.2.2.dist-info/entry_points.txt
cliriculum-0.2.2.dist-info/top_level.txt
cliriculum-0.2.2.dist-info/RECORD
