Metadata-Version: 2.1
Name: cliriculum
Version: 0.2.2
Summary: A python cli tool to rapidly create an html or PDF resume
License: MIT License
Project-URL: homepage, https://github.com/sondalex/cliriculum
Project-URL: documentation, https://sondalex.github.io/cliriculum
Requires-Python: >=3.9
License-File: LICENSE.md
Requires-Dist: mistletoe >=1.0.1
Provides-Extra: doc
Requires-Dist: myst-parser >=0.18.1 ; extra == 'doc'
Requires-Dist: sphinx >=5.3.0 ; extra == 'doc'
Requires-Dist: furo >=2022.12.7 ; extra == 'doc'
Requires-Dist: myst-nb >=0.17.1 ; extra == 'doc'
Requires-Dist: pdf2image ; extra == 'doc'
Requires-Dist: ipykernel ; extra == 'doc'
Provides-Extra: test
Requires-Dist: pytest >=7.2.1 ; extra == 'test'
Requires-Dist: pypdf >=3.3.0 ; extra == 'test'
Requires-Dist: requests >=2.28.2 ; extra == 'test'
